LICENSE
MANIFEST.in
Makefile
README.md
setup.py
doc/Makefile
doc/source/api.rst
doc/source/conf.py
doc/source/index.rst
doc/source/quick_start.rst
doc/source/_static/nature.css
nervanagpu/__init__.py
nervanagpu/float_ew.py
nervanagpu/layers.py
nervanagpu/nervanagpu.py
nervanagpu.egg-info/PKG-INFO
nervanagpu.egg-info/SOURCES.txt
nervanagpu.egg-info/dependency_links.txt
nervanagpu.egg-info/requires.txt
nervanagpu.egg-info/top_level.txt
nervanagpu/kernels/cu/hconv_bprop_C128_N64.cu
nervanagpu/kernels/cu/hconv_fprop_K64_N64.cu
nervanagpu/kernels/cu/hconv_fprop_s8_K64_N64.cu
nervanagpu/kernels/cu/hconv_fprop_u8_K64_N64.cu
nervanagpu/kernels/cu/hconv_updat_C128_K128.cu
nervanagpu/kernels/cu/hconv_updat_C64_K64.cu
nervanagpu/kernels/cu/hconv_updat_s8_C64_K64.cu
nervanagpu/kernels/cu/hconv_updat_u8_C64_K64.cu
nervanagpu/kernels/cu/hgemm_nn_128x128.cu
nervanagpu/kernels/cu/hgemm_nn_128x32.cu
nervanagpu/kernels/cu/hgemm_nn_128x64.cu
nervanagpu/kernels/cu/hgemm_nn_vec_128x128.cu
nervanagpu/kernels/cu/hgemm_nn_vec_128x32.cu
nervanagpu/kernels/cu/hgemm_nn_vec_128x64.cu
nervanagpu/kernels/cu/hgemm_nt_128x128.cu
nervanagpu/kernels/cu/hgemm_nt_vec_128x128.cu
nervanagpu/kernels/cu/hgemm_tn_128x128.cu
nervanagpu/kernels/cu/hgemm_tn_128x32.cu
nervanagpu/kernels/cu/hgemm_tn_128x64.cu
nervanagpu/kernels/cu/hgemm_tn_vec_128x128.cu
nervanagpu/kernels/cu/hgemm_tn_vec_128x16.cu
nervanagpu/kernels/cu/hgemm_tn_vec_128x32.cu
nervanagpu/kernels/cu/hgemm_tn_vec_128x64.cu
nervanagpu/kernels/cu/hpool_max.cu
nervanagpu/kernels/cu/sconv_bprop_C128_N64.cu
nervanagpu/kernels/cu/sconv_fprop_K64_N64.cu
nervanagpu/kernels/cu/sconv_fprop_s8_K64_N64.cu
nervanagpu/kernels/cu/sconv_fprop_u8_K64_N64.cu
nervanagpu/kernels/cu/sconv_updat_C128_K128.cu
nervanagpu/kernels/cu/sconv_updat_C128_K64.cu
nervanagpu/kernels/cu/sconv_updat_s8_C128_K64.cu
nervanagpu/kernels/cu/sconv_updat_u8_C128_K64.cu
nervanagpu/kernels/cu/sgemm_nn_128x128.cu
nervanagpu/kernels/cu/sgemm_nn_128x32.cu
nervanagpu/kernels/cu/sgemm_nn_128x64.cu
nervanagpu/kernels/cu/sgemm_nn_vec_128x128.cu
nervanagpu/kernels/cu/sgemm_nn_vec_128x32.cu
nervanagpu/kernels/cu/sgemm_nn_vec_128x64.cu
