Metadata-Version: 1.0
Name: nervanagpu
Version: 0.3.1
Summary: Python bindings for Nervana GPU kernels
Home-page: https://github.com/nervanasys/nervanagpu
Author: Nervana Systems
Author-email: UNKNOWN
License: (see LICENSE document)
Platform: UNKNOWN
